flames/__init__.py
flames/codes.py
flames-1.0.dist-info/DESCRIPTION.rst
flames-1.0.dist-info/METADATA
flames-1.0.dist-info/RECORD
flames-1.0.dist-info/WHEEL
flames-1.0.dist-info/metadata.json
flames-1.0.dist-info/top_level.txt
