Metadata-Version: 2.0
Name: flames
Version: 1.0
Summary: Compute the FLAMES value with amazing results using the flames module in python
Home-page: https://github.com/VaasuDevanS/flames
Author: Vaasu Devan S
Author-email: vaasuceg.96@gmail.com
License: GNU-GPL
Platform: UNKNOWN
Classifier: Operating System :: OS Independent
Classifier: Programming Language :: Python
Classifier: Programming Language :: Python :: 2.6
Classifier: Programming Language :: Python :: 2.7
Classifier: Programming Language :: Python :: 3
Classifier: Programming Language :: Python :: 3.3
Classifier: Programming Language :: Python :: 3.4
Classifier: Programming Language :: Python :: 3.5
Classifier: Programming Language :: Python :: 3.6
